[
  {
    "template_path": "I:/MyCode/FAA-extension/我.png",
    "tolerance": 0.95,
    "interval": 0.1,
    "timeout": 10.0,
    "after_sleep": 0.5,
    "check_enabled": false,
    "source_range": [
      0,
      0,
      950,
      600
    ]
  },
  {
    "template_path": "I:/MyCode/FAA-extension/2.png",
    "tolerance": 0.95,
    "interval": 0.1,
    "timeout": 10.0,
    "after_sleep": 0.5,
    "check_enabled": false,
    "source_range": [
      0,
      0,
      950,
      600
    ]
  },
  {
    "template_path": "I:/MyCode/FAA-extension/3.png",
    "tolerance": 0.95,
    "interval": 0.1,
    "timeout": 10.0,
    "after_sleep": 0.5,
    "check_enabled": false,
    "source_range": [
      0,
      0,
      950,
      600
    ]
  }
]